busrtworker/__init__.py
busrtworker/app.py
busrtworker/boostrap.py
busrtworker/busrt/__init__.py
busrtworker/busrt/busrt_client.py
busrtworker/busrt/busrt_rpc.py
busrtworker/busrt/msgutils.py
busrtworker/kink/__init__.py
busrtworker/kink/__verstion__.py
busrtworker/kink/container.py
busrtworker/kink/errors/__init__.py
busrtworker/kink/errors/conainer_error.py
busrtworker/kink/errors/execution_error.py
busrtworker/kink/errors/resolver_error.py
busrtworker/kink/errors/service_error.py
busrtworker/kink/inject.py
busrtworker/kink/py.typed
busrtworker/scheduler/__init__.py
busrtworker/tree.py
busrt_worker-0.1.7.dist-info/LICENSE
busrt_worker-0.1.7.dist-info/METADATA
busrt_worker-0.1.7.dist-info/WHEEL
busrt_worker-0.1.7.dist-info/RECORD
