Metadata-Version: 2.1
Name: busrt-worker
Version: 0.1.7
Summary: busrt-worker is a Python-based async busrt message handle framework
Home-page: https://git.loom.run/Coder/amqp-worker
License: MIT
Keywords: busrt,message,rpc
Author: JimZhang
Author-email: zzl22100048@gmail.com
Requires-Python: >=3.10,<4.0
Classifier: License :: OSI Approved :: MIT License
Classifier: Programming Language :: Python :: 3
Classifier: Programming Language :: Python :: 3.10
Classifier: Programming Language :: Python :: 3.11
Requires-Dist: cramjam (>=2.6.2,<3.0.0)
Requires-Dist: loguru (>=0.7.0,<0.8.0)
Requires-Dist: msgpack (>=1.0.5,<2.0.0)
Project-URL: Repository, https://git.loom.run/Coder/amqp-worker
